donnes_des_sous/__init__.py
donnes_des_sous/banque.py
donnes_des_sous-0.1.1.dist-info/WHEEL
donnes_des_sous-0.1.1.dist-info/entry_points.txt
donnes_des_sous-0.1.1.dist-info/METADATA
donnes_des_sous-0.1.1.dist-info/RECORD
