Metadata-Version: 2.3
Name: donnes-des-sous
Version: 0.1.1
Summary: Add your description here
Author: Guillaume Chervet
Author-email: Guillaume Chervet <guillaume.chervet@gmail.com>
Requires-Dist: httpx==0.28.1
Requires-Python: >=3.12
